zxcvbn_password/__init__.py
zxcvbn_password/fields.py
zxcvbn_password/utils.py
zxcvbn_password/validators.py
zxcvbn_password/widgets.py
zxcvbn_password/static/zxcvbn_password/js/password_strength.js
zxcvbn_password/static/zxcvbn_password/js/zxcvbn-async.js
zxcvbn_password/static/zxcvbn_password/js/zxcvbn.js
django_zxcvbn_password-2.1.1.dist-info/AUTHORS.rst
django_zxcvbn_password-2.1.1.dist-info/LICENSE
django_zxcvbn_password-2.1.1.dist-info/METADATA
django_zxcvbn_password-2.1.1.dist-info/WHEEL
django_zxcvbn_password-2.1.1.dist-info/top_level.txt
django_zxcvbn_password-2.1.1.dist-info/RECORD
