Metadata-Version: 2.1
Name: django-zxcvbn-password
Version: 2.1.1
Summary: Back-end and Front-end password validation with ZXCVBN.
Home-page: https://github.com/Pawamoy/django-zxcvbn-password
Author: Timothee Mazzucotelli
Author-email: timothee.mazzucotelli@gmail.com
License: ISC
Keywords: django,zxcvbn,password
Platform: UNKNOWN
Classifier: Development Status :: 5 - Production/Stable
Classifier: Intended Audience :: Developers
Classifier: License :: OSI Approved :: ISC License (ISCL)
Classifier: Operating System :: Unix
Classifier: Framework :: Django
Classifier: Programming Language :: Python
Classifier: Programming Language :: Python :: 2.7
Classifier: Programming Language :: Python :: 3
Classifier: Programming Language :: Python :: 3.4
Classifier: Programming Language :: Python :: 3.5
Classifier: Programming Language :: Python :: 3.6
Classifier: Programming Language :: Python :: Implementation :: PyPy
Classifier: Topic :: Utilities
License-File: LICENSE
License-File: AUTHORS.rst
